orca/__init__.py
orca/config.py
orca/requirements.txt
orca/adapters/__init__.py
orca/adapters/lambda_adapter.py
orca/common/__init__.py
orca/common/decorators.py
orca/common/exceptions.py
orca/common/logging_config.py
orca/common/type_guards.py
orca/core/__init__.py
orca/core/handler.py
orca/core/session/__init__.py
orca/core/session/audio_ops.py
orca/core/session/button_ops.py
orca/core/session/card_ops.py
orca/core/session/core.py
orca/core/session/escalation_ops.py
orca/core/session/image_ops.py
orca/core/session/loading_ops.py
orca/core/session/location_ops.py
orca/core/session/tracing_ops.py
orca/core/session/usage_ops.py
orca/core/session/video_ops.py
orca/domain/__init__.py
orca/domain/interfaces.py
orca/domain/models.py
orca/factories/__init__.py
orca/factories/stream_client_factory.py
orca/helpers/__init__.py
orca/helpers/button_helper.py
orca/helpers/button_utils.py
orca/infrastructure/__init__.py
orca/infrastructure/api_client.py
orca/infrastructure/centrifugo_client.py
orca/infrastructure/dev_stream_client.py
orca/patterns/__init__.py
orca/patterns/builder.py
orca/patterns/context.py
orca/patterns/middleware.py
orca/services/__init__.py
orca/services/buffer_manager.py
orca/services/button_renderer.py
orca/services/error_handler.py
orca/services/escalation_service.py
orca/services/loading_marker_provider.py
orca/services/response_builder.py
orca/services/tracing_service.py
orca/services/usage_tracker.py
orca/storage/README.md
orca/storage/__init__.py
orca/storage/base_client.py
orca/storage/bucket_service.py
orca/storage/client.py
orca/storage/file_service.py
orca/storage/permission_service.py
orca/utils/__init__.py
orca/utils/app_utils.py
orca/utils/environment.py
orca/utils/files.py
orca/utils/lambda_utils.py
orca/utils/memory.py
orca/utils/prompts.py
orca/utils/response_handler.py
orca/utils/tools.py
orca/utils/variables.py
orca/web/__init__.py
orca/web/app_factory.py
orca/web/endpoints.py
orca_platform_sdk_ui-1.0.7.dist-info/licenses/LICENSE
orca_platform_sdk_ui-1.0.7.dist-info/METADATA
orca_platform_sdk_ui-1.0.7.dist-info/WHEEL
orca_platform_sdk_ui-1.0.7.dist-info/top_level.txt
orca_platform_sdk_ui-1.0.7.dist-info/RECORD
