Metadata-Version: 2.4
Name: orca-platform-sdk-ui
Version: 1.0.7
Summary: Clean, minimal package for Orca platform integration
Home-page: https://github.com/Orcapt/orca-pip
Author: Orca Team
Author-email: Orca Team <support@orcaolatform.ai>
Maintainer-email: Orca Team <support@orcaolatform.ai>
License: MIT
Project-URL: Homepage, https://github.com/Orcapt/orca-pip
Project-URL: Documentation, https://github.com/Orcapt/orca-pip#readme
Project-URL: Repository, https://github.com/Orcapt/orca-pip
Project-URL: Bug Tracker, https://github.com/Orcapt/orca-pip/issues
Keywords: orca,ai,chatbot,platform,integration,fastapi,real-time
Classifier: Development Status :: 4 - Beta
Classifier: Intended Audience :: Developers
Classifier: Operating System :: OS Independent
Classifier: Programming Language :: Python :: 3
Classifier: Programming Language :: Python :: 3.8
Classifier: Programming Language :: Python :: 3.9
Classifier: Programming Language :: Python :: 3.10
Classifier: Programming Language :: Python :: 3.11
Classifier: Programming Language :: Python :: 3.12
Classifier: Programming Language :: Python :: 3.13
Classifier: Topic :: Software Development :: Libraries :: Python Modules
Classifier: Topic :: Communications :: Chat
Classifier: Topic :: Internet :: WWW/HTTP :: HTTP Servers
Classifier: Framework :: FastAPI
Requires-Python: >=3.8
License-File: LICENSE
Requires-Dist: requests>=2.25.0
Requires-Dist: pydantic>=2.0.0
Provides-Extra: web
Requires-Dist: fastapi>=0.100.0; extra == "web"
Requires-Dist: uvicorn>=0.20.0; extra == "web"
Provides-Extra: dev
Requires-Dist: pytest>=6.0; extra == "dev"
Requires-Dist: pytest-asyncio>=0.18.0; extra == "dev"
Requires-Dist: black>=21.0; extra == "dev"
Requires-Dist: flake8>=3.8; extra == "dev"
Requires-Dist: mypy>=0.800; extra == "dev"
Dynamic: author
Dynamic: home-page
Dynamic: license-file
Dynamic: requires-python
